TRIdentification/__init__.py
TRIdentification/exception.py
TRIdentification/service/__init__.py
TRIdentification/service/helper.py
TRIdentification/service/identity_service.py
TRIdentificationValidator-0.0.3.dist-info/LICENSE
TRIdentificationValidator-0.0.3.dist-info/METADATA
TRIdentificationValidator-0.0.3.dist-info/WHEEL
TRIdentificationValidator-0.0.3.dist-info/top_level.txt
TRIdentificationValidator-0.0.3.dist-info/RECORD
