Metadata-Version: 2.1
Name: TRIdentificationValidator
Version: 0.0.3
Summary: TRIdentificationValidator Python package
Home-page: https://github.com/blueromans/TRIdentificationValidator.git
Author: Yaşar Özyurt
Author-email: blueromans@gmail.com
Project-URL: Bug Tracker, https://github.com/blueromans/TRIdentificationValidator/issues
Classifier: Programming Language :: Python :: 3
Classifier: License :: OSI Approved :: MIT License
Classifier: Operating System :: OS Independent
Requires-Python: >=3.6
License-File: LICENSE
Requires-Dist: zeep
Requires-Dist: urllib3 (==1.26.6)
